sphinxcontrib_sheeptext/__init__.py
sphinxcontrib_sheeptext/sphinxcontrib_sheeptext.py
sphinxcontrib_sheeptext-0.1.0.dist-info/WHEEL
sphinxcontrib_sheeptext-0.1.0.dist-info/METADATA
sphinxcontrib_sheeptext-0.1.0.dist-info/RECORD
